riot_api/__init__.py
riot_api/api/__init__.py
riot_api/api/_request_executor.py
riot_api/api/_response_handler.py
riot_api/api/get/__init__.py
riot_api/api/get/champion_mastery_v4.py
riot_api/api/get/champion_v3.py
riot_api/api/get/league_v4.py
riot_api/api/get/lol_status_v3.py
riot_api/api/get/match_v4.py
riot_api/api/get/spectator_v4.py
riot_api/api/get/summoner_v4.py
riot_api/api/get/third_party_code_v4.py
riot_api/api/get/tournament_stub_v4.py
riot_api/api/get/tournament_v4.py
riot_api/api/get/endpoints/__init__.py
riot_api/api/get/endpoints/endpoints_v3.json
riot_api/api/get/endpoints/endpoints_v4.json
riot_api/api/post/__init__.py
riot_api/api/post/tournament_stub_v4.py
riot_api/api/post/tournament_v4.py
riot_api/api/post/endpoints/__init__.py
riot_api/api/post/endpoints/endpoints_v4.json
riot_api/api/put/__init__.py
riot_api/api/put/tournaments_v4.py
riot_api/api/put/endpoints/__init__.py
riot_api/api/put/endpoints/endpoints_v4.json
tests/__init__.py
tests/test_response_handler.py
Riot_API-0.0.14.dist-info/LICENSE
Riot_API-0.0.14.dist-info/METADATA
Riot_API-0.0.14.dist-info/WHEEL
Riot_API-0.0.14.dist-info/top_level.txt
Riot_API-0.0.14.dist-info/RECORD
