Metadata-Version: 2.1
Name: Riot-API
Version: 0.0.14
Summary: A thin wrapper around the Riot Games API for League of Legends.
Home-page: https://github.com/Alex-Weatherhead/riot_api
Author: Kristian Alexander Weatherhead
License: LICENSE
Platform: UNKNOWN
Requires-Dist: requests (>=2.20.1)
